[{
	"ID": "10",
	"___FK_cb2e67451ade727e0ae052e9": "1",
	"Name": "Flat Screen",
	"ReqQuantity": 2,
	"ReqDelivery": "May 2, 2016",
	"AvailableQuantity": 10,
	"EstDelivery": "May 9, 2016",
	"Price": 650,
	"SubTotal": 2133.77
}, {
	"ID": "20",
	"___FK_cb2e67451ade727e0ae052e9": "1",
	"Name": "Keyboard",
	"ReqQuantity": 1,
	"ReqDelivery": "May 2, 2016",
	"AvailableQuantity": 20,
	"EstDelivery": "May 9, 2016",
	"Price": 15,
	"SubTotal": 7802.36
}, {
	"ID": "30",
	"___FK_cb2e67451ade727e0ae052e9": "1",
	"Name": "Mouse",
	"ReqQuantity": 1,
	"ReqDelivery": "May 2, 2016",
	"AvailableQuantity": 3,
	"EstDelivery": "May 9, 2016",
	"Price": 10,
	"SubTotal": 8168.48
}, {
	"ID": "40",
	"___FK_cb2e67451ade727e0ae052e9": "2",
	"Name": "Laptop",
	"ReqQuantity": 1,
	"ReqDelivery": "May 2, 2016",
	"AvailableQuantity": 15,
	"EstDelivery": "May 9, 2016",
	"Price": 856,
	"SubTotal": 8161.41
}, {
	"ID": "50",
	"___FK_cb2e67451ade727e0ae052e9": "2",
	"Name": "Flat Screen",
	"ReqQuantity": 1,
	"ReqDelivery": "May 2, 2016",
	"AvailableQuantity": 10,
	"EstDelivery": "May 9, 2016",
	"Price": 650,
	"SubTotal": 48.68
}, {
	"ID": "110",
	"___FK_cb2e67451ade727e0ae052e9": "3",
	"Name": "Keyboard",
	"ReqQuantity": 1,
	"ReqDelivery": "May 2, 2016",
	"AvailableQuantity": 20,
	"EstDelivery": "May 9, 2016",
	"Price": 15,
	"SubTotal": 2301.24
}, {
	"ID": "120",
	"___FK_cb2e67451ade727e0ae052e9": "4",
	"Name": "Mouse",
	"ReqQuantity": 1,
	"ReqDelivery": "May 2, 2016",
	"AvailableQuantity": 3,
	"EstDelivery": "May 9, 2016",
	"Price": 10,
	"SubTotal": 7031.42
}, {
	"ID": "130",
	"___FK_cb2e67451ade727e0ae052e9": "4",
	"Name": "Laptop",
	"ReqQuantity": 1,
	"ReqDelivery": "May 2, 2016",
	"AvailableQuantity": 15,
	"EstDelivery": "May 9, 2016",
	"Price": 856,
	"SubTotal": 5086.71
}, {
	"ID": "140",
	"___FK_cb2e67451ade727e0ae052e9": "5",
	"Name": "Flat Screen",
	"ReqQuantity": 1,
	"ReqDelivery": "May 2, 2016",
	"AvailableQuantity": 10,
	"EstDelivery": "May 9, 2016",
	"Price": 650,
	"SubTotal": 1941.3
}, {
	"ID": "150",
	"___FK_cb2e67451ade727e0ae052e9": "5",
	"Name": "Keyboard",
	"ReqQuantity": 1,
	"ReqDelivery": "May 2, 2016",
	"AvailableQuantity": 20,
	"EstDelivery": "May 9, 2016",
	"Price": 15,
	"SubTotal": 7768.23
}, {
	"ID": "210",
	"___FK_cb2e67451ade727e0ae052e9": "6",
	"Name": "Mouse",
	"ReqQuantity": 2,
	"ReqDelivery": "May 2, 2016",
	"AvailableQuantity": 3,
	"EstDelivery": "May 9, 2016",
	"Price": 10,
	"SubTotal": 6015.94
}, {
	"ID": "220",
	"___FK_cb2e67451ade727e0ae052e9": "6",
	"Name": "Laptop",
	"ReqQuantity": 1,
	"ReqDelivery": "May 2, 2016",
	"AvailableQuantity": 15,
	"EstDelivery": "May 9, 2016",
	"Price": 856,
	"SubTotal": 5230.3
}]